{
  "count": 9,
  "generated": "2026-07-16T10:16:35Z",
  "pages": {
    "alpha": {
      "sessions": 14,
      "users": 13,
      "views": 13
    },
    "cocktail-2": {
      "sessions": 6,
      "users": 6,
      "views": 7
    },
    "dhamaal-4": {
      "sessions": 31,
      "users": 19,
      "views": 35
    },
    "dhurandhar-the-revenge": {
      "sessions": 1,
      "users": 1,
      "views": 1
    },
    "main-vaapas-aaunga": {
      "sessions": 3,
      "users": 3,
      "views": 3
    },
    "mardaani-3": {
      "sessions": 1,
      "users": 1,
      "views": 1
    },
    "supergirl": {
      "sessions": 1,
      "users": 1,
      "views": 1
    },
    "tera-mera-nata": {
      "sessions": 2,
      "users": 1,
      "views": 2
    },
    "welcome-to-the-jungle": {
      "sessions": 29,
      "users": 20,
      "views": 30
    }
  },
  "property": "538422281",
  "range": "yesterday",
  "section": "hindi-boxoffice",
  "totalSessions": 88,
  "totalUsers": 65,
  "totalViews": 93
}