{
  "count": 8,
  "generated": "2026-07-10T17:45:27Z",
  "pages": {
    "alpha": {
      "sessions": 25,
      "users": 15,
      "views": 26
    },
    "baby-do-die-do": {
      "sessions": 1,
      "users": 1,
      "views": 1
    },
    "border-2": {
      "sessions": 1,
      "users": 1,
      "views": 1
    },
    "cocktail-2": {
      "sessions": 6,
      "users": 6,
      "views": 5
    },
    "dhamaal-4": {
      "sessions": 49,
      "users": 23,
      "views": 43
    },
    "navya-chakra": {
      "sessions": 1,
      "users": 1,
      "views": 1
    },
    "tera-mera-nata": {
      "sessions": 1,
      "users": 1,
      "views": 1
    },
    "welcome-to-the-jungle": {
      "sessions": 46,
      "users": 25,
      "views": 46
    }
  },
  "property": "538422281",
  "range": "today",
  "section": "hindi-boxoffice",
  "totalSessions": 130,
  "totalUsers": 73,
  "totalViews": 124
}