{
  "count": 4,
  "generated": "2026-07-05T10:09:27Z",
  "pages": {
    "alpha": {
      "sessions": 37,
      "users": 24,
      "views": 71
    },
    "bharat-bhhagya-viddhaata": {
      "sessions": 1,
      "users": 1,
      "views": 1
    },
    "cocktail-2": {
      "sessions": 5,
      "users": 5,
      "views": 6
    },
    "welcome-to-the-jungle": {
      "sessions": 60,
      "users": 29,
      "views": 70
    }
  },
  "property": "538422281",
  "range": "today",
  "section": "hindi-boxoffice",
  "totalSessions": 103,
  "totalUsers": 59,
  "totalViews": 148
}