{
  "count": 6,
  "generated": "2026-07-02T10:35:09Z",
  "pages": {
    "cocktail-2": {
      "sessions": 4,
      "users": 4,
      "views": 3
    },
    "governor": {
      "sessions": 1,
      "users": 1,
      "views": 1
    },
    "hai-jawani-toh-ishq-hona-hai": {
      "sessions": 1,
      "users": 1,
      "views": 1
    },
    "navya-chakra": {
      "sessions": 3,
      "users": 3,
      "views": 3
    },
    "peddi": {
      "sessions": 1,
      "users": 1,
      "views": 1
    },
    "welcome-to-the-jungle": {
      "sessions": 42,
      "users": 26,
      "views": 46
    }
  },
  "property": "538422281",
  "range": "today",
  "section": "hindi-boxoffice",
  "totalSessions": 52,
  "totalUsers": 36,
  "totalViews": 55
}