{
  "count": 5,
  "generated": "2026-07-15T08:23:59Z",
  "pages": {
    "alpha": {
      "sessions": 7,
      "users": 7,
      "views": 7
    },
    "dhamaal-4": {
      "sessions": 9,
      "users": 8,
      "views": 9
    },
    "main-vaapas-aaunga": {
      "sessions": 2,
      "users": 2,
      "views": 2
    },
    "supergirl": {
      "sessions": 1,
      "users": 1,
      "views": 1
    },
    "welcome-to-the-jungle": {
      "sessions": 7,
      "users": 7,
      "views": 6
    }
  },
  "property": "538422281",
  "range": "today",
  "section": "hindi-boxoffice",
  "totalSessions": 26,
  "totalUsers": 25,
  "totalViews": 25
}