{
  "count": 10,
  "generated": "2026-07-21T12:25:59Z",
  "pages": {
    "live-boxoffice": {
      "sessions": 6,
      "users": 4,
      "views": 14
    },
    "live-boxoffice/arco-alco": {
      "sessions": 1,
      "users": 1,
      "views": 1
    },
    "live-boxoffice/dhurandhar": {
      "sessions": 20,
      "users": 20,
      "views": 19
    },
    "live-boxoffice/jawan": {
      "sessions": 1,
      "users": 1,
      "views": 1
    },
    "live-boxoffice/kalki-2898-ad": {
      "sessions": 1,
      "users": 1,
      "views": 1
    },
    "live-boxoffice/pathaan": {
      "sessions": 1,
      "users": 1,
      "views": 1
    },
    "live-boxoffice/pushpa-2-the-rule": {
      "sessions": 1,
      "users": 1,
      "views": 1
    },
    "live-boxoffice/rrr-rise-roar-revolt": {
      "sessions": 1,
      "users": 1,
      "views": 1
    },
    "live-boxoffice/saaho": {
      "sessions": 2,
      "users": 2,
      "views": 2
    },
    "live-boxoffice/the-queen-of-teleshopping-a-channel-dedicated-to-aoyi-haruka-s-cases": {
      "sessions": 1,
      "users": 1,
      "views": 1
    }
  },
  "property": "538422281",
  "range": "today",
  "section": "japan",
  "totalSessions": 35,
  "totalUsers": 33,
  "totalViews": 42
}