{
  "count": 8,
  "generated": "2026-07-19T11:16:12Z",
  "pages": {
    "live-boxoffice/jana-nayagan-22-july-2026": {
      "sessions": 1,
      "users": 1,
      "views": 1
    },
    "live-boxoffice/jana-nayagan-23-july-2026": {
      "sessions": 235,
      "users": 96,
      "views": 384
    },
    "live-boxoffice/jana-nayagan-24-july-2026": {
      "sessions": 32,
      "users": 24,
      "views": 36
    },
    "live-boxoffice/jana-nayagan-25-july-2026": {
      "sessions": 24,
      "users": 19,
      "views": 30
    },
    "live-boxoffice/jana-nayagan-26-july-2026": {
      "sessions": 22,
      "users": 16,
      "views": 25
    },
    "live-boxoffice/jana-nayagan-27-july-2026": {
      "sessions": 7,
      "users": 7,
      "views": 7
    },
    "live-boxoffice/jana-nayagan-28-july-2026": {
      "sessions": 3,
      "users": 3,
      "views": 5
    },
    "live-boxoffice/jana-nayagan-29-july-2026": {
      "sessions": 1,
      "users": 1,
      "views": 2
    }
  },
  "property": "538422281",
  "range": "today",
  "section": "malaysia",
  "totalSessions": 325,
  "totalUsers": 167,
  "totalViews": 490
}