{
  "count": 4,
  "generated": "2026-07-23T15:14:14Z",
  "pages": {
    "advance-bookings": {
      "sessions": 5,
      "users": 4,
      "views": 37
    },
    "live-boxoffice": {
      "sessions": 28,
      "users": 20,
      "views": 127
    },
    "live-boxoffice/gauthali": {
      "sessions": 1,
      "users": 1,
      "views": 1
    },
    "live-boxoffice/the-odyssey": {
      "sessions": 1,
      "users": 1,
      "views": 1
    }
  },
  "property": "538422281",
  "range": "today",
  "section": "nepal",
  "totalSessions": 35,
  "totalUsers": 26,
  "totalViews": 166
}