{
  "count": 8,
  "generated": "2026-07-24T06:31:05Z",
  "pages": {
    "advance-bookings/jana-nayagan-22-july-2026": {
      "sessions": 9,
      "users": 7,
      "views": 14
    },
    "advance-bookings/jana-nayagan-23-july-2026": {
      "sessions": 9,
      "users": 5,
      "views": 21
    },
    "advance-bookings/jana-nayagan-24-july-2026": {
      "sessions": 5,
      "users": 4,
      "views": 11
    },
    "advance-bookings/jana-nayagan-25-july-2026": {
      "sessions": 3,
      "users": 3,
      "views": 3
    },
    "index": {
      "sessions": 11,
      "users": 11,
      "views": 15
    },
    "live-boxoffice/jana-nayagan-22-july-2026": {
      "sessions": 2,
      "users": 2,
      "views": 2
    },
    "live-boxoffice/jana-nayagan-23-july-2026": {
      "sessions": 2,
      "users": 1,
      "views": 3
    },
    "live-boxoffice/jana-nayagan-24-july-2026": {
      "sessions": 1,
      "users": 1,
      "views": 1
    }
  },
  "property": "538422281",
  "range": "today",
  "section": "usa",
  "totalSessions": 42,
  "totalUsers": 34,
  "totalViews": 70
}