{
  "date": "2026-07-18",
  "last_updated": "2026-07-13T18:57:59.267968+05:30",
  "movies": {
    "The Odyssey": {
      "gross": 0,
      "occupancy": null,
      "seats_type": {
        "with_gross": {
          "breakdown": [],
          "gross": 0,
          "shows": 0,
          "tickets_sold": 0
        },
        "without_gross": {
          "breakdown": [
            {
              "gross": 0,
              "movie": "The Odyssey",
              "screen": "Dolby Atmos",
              "showid": "5665",
              "tickets_sold": 0,
              "time": "11:30 AM",
              "venue": "Girija Theatre"
            },
            {
              "gross": 0,
              "movie": "The Odyssey",
              "screen": "Dolby Atmos",
              "showid": "5666",
              "tickets_sold": 0,
              "time": "03:00 PM",
              "venue": "Girija Theatre"
            },
            {
              "gross": 0,
              "movie": "The Odyssey",
              "screen": "Dolby Atmos",
              "showid": "5667",
              "tickets_sold": 0,
              "time": "06:30 PM",
              "venue": "Girija Theatre"
            },
            {
              "gross": 0,
              "movie": "The Odyssey",
              "screen": "Dolby Atmos",
              "showid": "5668",
              "tickets_sold": 0,
              "time": "10:00 PM",
              "venue": "Girija Theatre"
            }
          ],
          "shows": 4,
          "tickets_sold": 0
        }
      },
      "show_breakdown": [
        {
          "gross": 0,
          "movie": "The Odyssey",
          "screen": "Dolby Atmos",
          "showid": "5665",
          "tickets_sold": 0,
          "time": "11:30 AM",
          "venue": "Girija Theatre"
        },
        {
          "gross": 0,
          "movie": "The Odyssey",
          "screen": "Dolby Atmos",
          "showid": "5666",
          "tickets_sold": 0,
          "time": "03:00 PM",
          "venue": "Girija Theatre"
        },
        {
          "gross": 0,
          "movie": "The Odyssey",
          "screen": "Dolby Atmos",
          "showid": "5667",
          "tickets_sold": 0,
          "time": "06:30 PM",
          "venue": "Girija Theatre"
        },
        {
          "gross": 0,
          "movie": "The Odyssey",
          "screen": "Dolby Atmos",
          "showid": "5668",
          "tickets_sold": 0,
          "time": "10:00 PM",
          "venue": "Girija Theatre"
        }
      ],
      "shows": 4,
      "tickets_sold": 0
    }
  },
  "verification": {
    "merged_movies": [
      {
        "aliases": [
          "VARAVU"
        ],
        "canonical": "VARAVU"
      },
      {
        "aliases": [
          "Evil Dead Burn"
        ],
        "canonical": "Evil Dead Burn"
      },
      {
        "aliases": [
          "Balan: The Boy"
        ],
        "canonical": "Balan: The Boy"
      },
      {
        "aliases": [
          "Idhayam Murali"
        ],
        "canonical": "Idhayam Murali"
      },
      {
        "aliases": [
          "I Nobody",
          "I, Nobody",
          "I,Nobody"
        ],
        "canonical": "I,Nobody"
      },
      {
        "aliases": [
          "SECRET OF KALINGA"
        ],
        "canonical": "SECRET OF KALINGA"
      },
      {
        "aliases": [
          "The Odyssey"
        ],
        "canonical": "The Odyssey"
      },
      {
        "aliases": [
          "Argentina vs England Semi Final 2"
        ],
        "canonical": "Argentina vs England Semi Final 2"
      },
      {
        "aliases": [
          "Kireedam"
        ],
        "canonical": "Kireedam"
      },
      {
        "aliases": [
          "FRANCE vs SPAIN Semi Final 1"
        ],
        "canonical": "FRANCE vs SPAIN Semi Final 1"
      }
    ]
  }
}