{
  "date": "2026-07-23",
  "last_updated": "2026-07-19T19:07:06.113514+05:30",
  "movies": {
    "Jana Nayagan": {
      "gross": 168150,
      "occupancy": null,
      "seats_type": {
        "with_gross": {
          "breakdown": [
            {
              "gross": 33000,
              "movie": "Jana Nayagan",
              "screen": "Aiswarya",
              "showid": "7780",
              "tickets_sold": 220,
              "time": "10:45 AM",
              "venue": "Aiswarya Cinemas"
            },
            {
              "gross": 22800,
              "movie": "Jana Nayagan",
              "screen": "Aiswarya",
              "showid": "7783",
              "tickets_sold": 152,
              "time": "09:15 PM",
              "venue": "Aiswarya Cinemas"
            },
            {
              "gross": 20550,
              "movie": "Jana Nayagan",
              "screen": null,
              "showid": "18913",
              "tickets_sold": 137,
              "time": "08:30 PM",
              "venue": "Puthet Cinemas"
            },
            {
              "gross": 11550,
              "movie": "Jana Nayagan",
              "screen": "SCREEN 1",
              "showid": "3440",
              "tickets_sold": 77,
              "time": "05:45 PM",
              "venue": "Fairyland Cinemas"
            },
            {
              "gross": 10800,
              "movie": "Jana Nayagan",
              "screen": "SCREEN 1",
              "showid": "3441",
              "tickets_sold": 72,
              "time": "09:30 PM",
              "venue": "Fairyland Cinemas"
            },
            {
              "gross": 9300,
              "movie": "Jana Nayagan",
              "screen": null,
              "showid": "18910",
              "tickets_sold": 62,
              "time": "10:00 AM",
              "venue": "Puthet Cinemas"
            },
            {
              "gross": 9450,
              "movie": "Jana Nayagan",
              "screen": "Aiswarya",
              "showid": "7781",
              "tickets_sold": 63,
              "time": "02:15 PM",
              "venue": "Aiswarya Cinemas"
            },
            {
              "gross": 8550,
              "movie": "Jana Nayagan",
              "screen": "SCREEN 1",
              "showid": "3438",
              "tickets_sold": 57,
              "time": "10:30 AM",
              "venue": "Fairyland Cinemas"
            },
            {
              "gross": 7950,
              "movie": "Jana Nayagan",
              "screen": null,
              "showid": "18912",
              "tickets_sold": 53,
              "time": "05:00 PM",
              "venue": "Puthet Cinemas"
            },
            {
              "gross": 6450,
              "movie": "Jana Nayagan [T]",
              "screen": "Dolby Atmos",
              "showid": "5691",
              "tickets_sold": 43,
              "time": "09:45 PM",
              "venue": "Girija Theatre"
            },
            {
              "gross": 6600,
              "movie": "Jana Nayagan [T]",
              "screen": "Dolby Atmos",
              "showid": "5690",
              "tickets_sold": 44,
              "time": "06:30 PM",
              "venue": "Girija Theatre"
            },
            {
              "gross": 4800,
              "movie": "Jana Nayagan",
              "screen": null,
              "showid": "18911",
              "tickets_sold": 32,
              "time": "01:30 PM",
              "venue": "Puthet Cinemas"
            },
            {
              "gross": 3150,
              "movie": "Jana Nayagan",
              "screen": "Cinema-1",
              "showid": "22402",
              "tickets_sold": 21,
              "time": "06:15 PM",
              "venue": "Davis Theatre"
            },
            {
              "gross": 3750,
              "movie": "Jana Nayagan",
              "screen": "Aiswarya",
              "showid": "7782",
              "tickets_sold": 25,
              "time": "05:45 PM",
              "venue": "Aiswarya Cinemas"
            },
            {
              "gross": 2550,
              "movie": "Jana Nayagan",
              "screen": "SCREEN 1",
              "showid": "3439",
              "tickets_sold": 17,
              "time": "02:00 PM",
              "venue": "Fairyland Cinemas"
            },
            {
              "gross": 2100,
              "movie": "Jana Nayagan",
              "screen": "Cinema-1",
              "showid": "22403",
              "tickets_sold": 14,
              "time": "09:45 PM",
              "venue": "Davis Theatre"
            },
            {
              "gross": 1800,
              "movie": "Jana Nayagan",
              "screen": "Cinema-1",
              "showid": "22401",
              "tickets_sold": 12,
              "time": "02:50 PM",
              "venue": "Davis Theatre"
            },
            {
              "gross": 1800,
              "movie": "Jana Nayagan",
              "screen": "Cinema-1",
              "showid": "22400",
              "tickets_sold": 12,
              "time": "11:30 AM",
              "venue": "Davis Theatre"
            },
            {
              "gross": 1050,
              "movie": "Jana Nayagan [T]",
              "screen": "Dolby Atmos",
              "showid": "5688",
              "tickets_sold": 7,
              "time": "11:30 AM",
              "venue": "Girija Theatre"
            },
            {
              "gross": 150,
              "movie": "Jana Nayagan [T]",
              "screen": "Dolby Atmos",
              "showid": "5689",
              "tickets_sold": 1,
              "time": "03:00 PM",
              "venue": "Girija Theatre"
            }
          ],
          "gross": 168150,
          "shows": 20,
          "tickets_sold": 1121
        },
        "without_gross": {
          "breakdown": [
            {
              "gross": 0,
              "movie": "Jana Nayagan",
              "screen": null,
              "showid": "18914",
              "tickets_sold": 0,
              "time": "11:45 PM",
              "venue": "Puthet Cinemas"
            }
          ],
          "shows": 1,
          "tickets_sold": 0
        }
      },
      "show_breakdown": [
        {
          "gross": 33000,
          "movie": "Jana Nayagan",
          "screen": "Aiswarya",
          "showid": "7780",
          "tickets_sold": 220,
          "time": "10:45 AM",
          "venue": "Aiswarya Cinemas"
        },
        {
          "gross": 22800,
          "movie": "Jana Nayagan",
          "screen": "Aiswarya",
          "showid": "7783",
          "tickets_sold": 152,
          "time": "09:15 PM",
          "venue": "Aiswarya Cinemas"
        },
        {
          "gross": 20550,
          "movie": "Jana Nayagan",
          "screen": null,
          "showid": "18913",
          "tickets_sold": 137,
          "time": "08:30 PM",
          "venue": "Puthet Cinemas"
        },
        {
          "gross": 11550,
          "movie": "Jana Nayagan",
          "screen": "SCREEN 1",
          "showid": "3440",
          "tickets_sold": 77,
          "time": "05:45 PM",
          "venue": "Fairyland Cinemas"
        },
        {
          "gross": 10800,
          "movie": "Jana Nayagan",
          "screen": "SCREEN 1",
          "showid": "3441",
          "tickets_sold": 72,
          "time": "09:30 PM",
          "venue": "Fairyland Cinemas"
        },
        {
          "gross": 9450,
          "movie": "Jana Nayagan",
          "screen": "Aiswarya",
          "showid": "7781",
          "tickets_sold": 63,
          "time": "02:15 PM",
          "venue": "Aiswarya Cinemas"
        },
        {
          "gross": 9300,
          "movie": "Jana Nayagan",
          "screen": null,
          "showid": "18910",
          "tickets_sold": 62,
          "time": "10:00 AM",
          "venue": "Puthet Cinemas"
        },
        {
          "gross": 8550,
          "movie": "Jana Nayagan",
          "screen": "SCREEN 1",
          "showid": "3438",
          "tickets_sold": 57,
          "time": "10:30 AM",
          "venue": "Fairyland Cinemas"
        },
        {
          "gross": 7950,
          "movie": "Jana Nayagan",
          "screen": null,
          "showid": "18912",
          "tickets_sold": 53,
          "time": "05:00 PM",
          "venue": "Puthet Cinemas"
        },
        {
          "gross": 6600,
          "movie": "Jana Nayagan [T]",
          "screen": "Dolby Atmos",
          "showid": "5690",
          "tickets_sold": 44,
          "time": "06:30 PM",
          "venue": "Girija Theatre"
        },
        {
          "gross": 6450,
          "movie": "Jana Nayagan [T]",
          "screen": "Dolby Atmos",
          "showid": "5691",
          "tickets_sold": 43,
          "time": "09:45 PM",
          "venue": "Girija Theatre"
        },
        {
          "gross": 4800,
          "movie": "Jana Nayagan",
          "screen": null,
          "showid": "18911",
          "tickets_sold": 32,
          "time": "01:30 PM",
          "venue": "Puthet Cinemas"
        },
        {
          "gross": 3750,
          "movie": "Jana Nayagan",
          "screen": "Aiswarya",
          "showid": "7782",
          "tickets_sold": 25,
          "time": "05:45 PM",
          "venue": "Aiswarya Cinemas"
        },
        {
          "gross": 3150,
          "movie": "Jana Nayagan",
          "screen": "Cinema-1",
          "showid": "22402",
          "tickets_sold": 21,
          "time": "06:15 PM",
          "venue": "Davis Theatre"
        },
        {
          "gross": 2550,
          "movie": "Jana Nayagan",
          "screen": "SCREEN 1",
          "showid": "3439",
          "tickets_sold": 17,
          "time": "02:00 PM",
          "venue": "Fairyland Cinemas"
        },
        {
          "gross": 2100,
          "movie": "Jana Nayagan",
          "screen": "Cinema-1",
          "showid": "22403",
          "tickets_sold": 14,
          "time": "09:45 PM",
          "venue": "Davis Theatre"
        },
        {
          "gross": 1800,
          "movie": "Jana Nayagan",
          "screen": "Cinema-1",
          "showid": "22401",
          "tickets_sold": 12,
          "time": "02:50 PM",
          "venue": "Davis Theatre"
        },
        {
          "gross": 1800,
          "movie": "Jana Nayagan",
          "screen": "Cinema-1",
          "showid": "22400",
          "tickets_sold": 12,
          "time": "11:30 AM",
          "venue": "Davis Theatre"
        },
        {
          "gross": 1050,
          "movie": "Jana Nayagan [T]",
          "screen": "Dolby Atmos",
          "showid": "5688",
          "tickets_sold": 7,
          "time": "11:30 AM",
          "venue": "Girija Theatre"
        },
        {
          "gross": 150,
          "movie": "Jana Nayagan [T]",
          "screen": "Dolby Atmos",
          "showid": "5689",
          "tickets_sold": 1,
          "time": "03:00 PM",
          "venue": "Girija Theatre"
        },
        {
          "gross": 0,
          "movie": "Jana Nayagan",
          "screen": null,
          "showid": "18914",
          "tickets_sold": 0,
          "time": "11:45 PM",
          "venue": "Puthet Cinemas"
        }
      ],
      "shows": 21,
      "tickets_sold": 1121
    }
  },
  "verification": {
    "merged_movies": [
      {
        "aliases": [
          "Jana Nayagan",
          "Jana Nayagan [T]"
        ],
        "canonical": "Jana Nayagan"
      },
      {
        "aliases": [
          "VARAVU",
          "Varavu"
        ],
        "canonical": "Varavu"
      },
      {
        "aliases": [
          "Unknown"
        ],
        "canonical": "Unknown"
      },
      {
        "aliases": [
          "I, Nobody",
          "I,Nobody"
        ],
        "canonical": "I,Nobody"
      },
      {
        "aliases": [
          "The Odyssey"
        ],
        "canonical": "The Odyssey"
      },
      {
        "aliases": [
          "Balan: The Boy"
        ],
        "canonical": "Balan: The Boy"
      },
      {
        "aliases": [
          "Anbe Diana"
        ],
        "canonical": "Anbe Diana"
      }
    ]
  }
}