{
  "date": "2026-07-26",
  "last_updated": "2026-07-23T09:49:31.678713+05:30",
  "movies": {
    "Jana Nayagan": {
      "gross": 24600,
      "occupancy": null,
      "seats_type": {
        "with_gross": {
          "breakdown": [
            {
              "gross": 6900,
              "movie": "Jana Nayagan",
              "screen": "Aiswarya",
              "showid": "7813",
              "tickets_sold": 46,
              "time": "10:45 AM",
              "venue": "Aiswarya Cinemas"
            },
            {
              "gross": 6450,
              "movie": "Jana Nayagan",
              "screen": "Aiswarya",
              "showid": "7814",
              "tickets_sold": 43,
              "time": "02:15 PM",
              "venue": "Aiswarya Cinemas"
            },
            {
              "gross": 4050,
              "movie": "Jana Nayagan",
              "screen": null,
              "showid": "18927",
              "tickets_sold": 27,
              "time": "05:00 PM",
              "venue": "Puthet Cinemas"
            },
            {
              "gross": 1350,
              "movie": "Jana Nayagan [T]",
              "screen": "Dolby Atmos",
              "showid": "5704",
              "tickets_sold": 9,
              "time": "03:00 PM",
              "venue": "Girija Theatre"
            },
            {
              "gross": 1350,
              "movie": "Jana Nayagan",
              "screen": "Aiswarya",
              "showid": "7816",
              "tickets_sold": 9,
              "time": "09:15 PM",
              "venue": "Aiswarya Cinemas"
            },
            {
              "gross": 1500,
              "movie": "Jana Nayagan",
              "screen": null,
              "showid": "18926",
              "tickets_sold": 10,
              "time": "01:30 PM",
              "venue": "Puthet Cinemas"
            },
            {
              "gross": 1350,
              "movie": "Jana Nayagan",
              "screen": null,
              "showid": "18925",
              "tickets_sold": 9,
              "time": "10:00 AM",
              "venue": "Puthet Cinemas"
            },
            {
              "gross": 600,
              "movie": "Jana Nayagan",
              "screen": null,
              "showid": "18928",
              "tickets_sold": 4,
              "time": "08:30 PM",
              "venue": "Puthet Cinemas"
            },
            {
              "gross": 450,
              "movie": "Jana Nayagan",
              "screen": "Aiswarya",
              "showid": "7815",
              "tickets_sold": 3,
              "time": "05:45 PM",
              "venue": "Aiswarya Cinemas"
            },
            {
              "gross": 150,
              "movie": "Jana Nayagan [T]",
              "screen": "Dolby Atmos",
              "showid": "5703",
              "tickets_sold": 1,
              "time": "11:30 AM",
              "venue": "Girija Theatre"
            },
            {
              "gross": 450,
              "movie": "Jana Nayagan [T]",
              "screen": "Dolby Atmos",
              "showid": "5705",
              "tickets_sold": 3,
              "time": "06:30 PM",
              "venue": "Girija Theatre"
            }
          ],
          "gross": 24600,
          "shows": 11,
          "tickets_sold": 164
        },
        "without_gross": {
          "breakdown": [
            {
              "gross": 0,
              "movie": "Jana Nayagan [T]",
              "screen": "Dolby Atmos",
              "showid": "5706",
              "tickets_sold": 0,
              "time": "09:45 PM",
              "venue": "Girija Theatre"
            },
            {
              "gross": 0,
              "movie": "Jana Nayagan",
              "screen": null,
              "showid": "18929",
              "tickets_sold": 0,
              "time": "11:45 PM",
              "venue": "Puthet Cinemas"
            }
          ],
          "shows": 2,
          "tickets_sold": 0
        }
      },
      "show_breakdown": [
        {
          "gross": 6900,
          "movie": "Jana Nayagan",
          "screen": "Aiswarya",
          "showid": "7813",
          "tickets_sold": 46,
          "time": "10:45 AM",
          "venue": "Aiswarya Cinemas"
        },
        {
          "gross": 6450,
          "movie": "Jana Nayagan",
          "screen": "Aiswarya",
          "showid": "7814",
          "tickets_sold": 43,
          "time": "02:15 PM",
          "venue": "Aiswarya Cinemas"
        },
        {
          "gross": 4050,
          "movie": "Jana Nayagan",
          "screen": null,
          "showid": "18927",
          "tickets_sold": 27,
          "time": "05:00 PM",
          "venue": "Puthet Cinemas"
        },
        {
          "gross": 1500,
          "movie": "Jana Nayagan",
          "screen": null,
          "showid": "18926",
          "tickets_sold": 10,
          "time": "01:30 PM",
          "venue": "Puthet Cinemas"
        },
        {
          "gross": 1350,
          "movie": "Jana Nayagan [T]",
          "screen": "Dolby Atmos",
          "showid": "5704",
          "tickets_sold": 9,
          "time": "03:00 PM",
          "venue": "Girija Theatre"
        },
        {
          "gross": 1350,
          "movie": "Jana Nayagan",
          "screen": "Aiswarya",
          "showid": "7816",
          "tickets_sold": 9,
          "time": "09:15 PM",
          "venue": "Aiswarya Cinemas"
        },
        {
          "gross": 1350,
          "movie": "Jana Nayagan",
          "screen": null,
          "showid": "18925",
          "tickets_sold": 9,
          "time": "10:00 AM",
          "venue": "Puthet Cinemas"
        },
        {
          "gross": 600,
          "movie": "Jana Nayagan",
          "screen": null,
          "showid": "18928",
          "tickets_sold": 4,
          "time": "08:30 PM",
          "venue": "Puthet Cinemas"
        },
        {
          "gross": 450,
          "movie": "Jana Nayagan",
          "screen": "Aiswarya",
          "showid": "7815",
          "tickets_sold": 3,
          "time": "05:45 PM",
          "venue": "Aiswarya Cinemas"
        },
        {
          "gross": 450,
          "movie": "Jana Nayagan [T]",
          "screen": "Dolby Atmos",
          "showid": "5705",
          "tickets_sold": 3,
          "time": "06:30 PM",
          "venue": "Girija Theatre"
        },
        {
          "gross": 150,
          "movie": "Jana Nayagan [T]",
          "screen": "Dolby Atmos",
          "showid": "5703",
          "tickets_sold": 1,
          "time": "11:30 AM",
          "venue": "Girija Theatre"
        },
        {
          "gross": 0,
          "movie": "Jana Nayagan [T]",
          "screen": "Dolby Atmos",
          "showid": "5706",
          "tickets_sold": 0,
          "time": "09:45 PM",
          "venue": "Girija Theatre"
        },
        {
          "gross": 0,
          "movie": "Jana Nayagan",
          "screen": null,
          "showid": "18929",
          "tickets_sold": 0,
          "time": "11:45 PM",
          "venue": "Puthet Cinemas"
        }
      ],
      "shows": 13,
      "tickets_sold": 164
    },
    "Jana Nayagan [T]": {
      "gross": 1500,
      "occupancy": null,
      "seats_type": {
        "with_gross": {
          "breakdown": [
            {
              "gross": 1350,
              "movie": "Jana Nayagan [T]",
              "screen": "Dolby Atmos",
              "showid": "5704",
              "tickets_sold": 9,
              "time": "03:00 PM",
              "venue": "Girija Theatre"
            },
            {
              "gross": 150,
              "movie": "Jana Nayagan [T]",
              "screen": "Dolby Atmos",
              "showid": "5703",
              "tickets_sold": 1,
              "time": "11:30 AM",
              "venue": "Girija Theatre"
            }
          ],
          "gross": 1500,
          "shows": 2,
          "tickets_sold": 10
        },
        "without_gross": {
          "breakdown": [
            {
              "gross": 0,
              "movie": "Jana Nayagan [T]",
              "screen": "Dolby Atmos",
              "showid": "5705",
              "tickets_sold": 0,
              "time": "06:30 PM",
              "venue": "Girija Theatre"
            },
            {
              "gross": 0,
              "movie": "Jana Nayagan [T]",
              "screen": "Dolby Atmos",
              "showid": "5706",
              "tickets_sold": 0,
              "time": "09:45 PM",
              "venue": "Girija Theatre"
            }
          ],
          "shows": 2,
          "tickets_sold": 0
        }
      },
      "show_breakdown": [
        {
          "gross": 1350,
          "movie": "Jana Nayagan [T]",
          "screen": "Dolby Atmos",
          "showid": "5704",
          "tickets_sold": 9,
          "time": "03:00 PM",
          "venue": "Girija Theatre"
        },
        {
          "gross": 150,
          "movie": "Jana Nayagan [T]",
          "screen": "Dolby Atmos",
          "showid": "5703",
          "tickets_sold": 1,
          "time": "11:30 AM",
          "venue": "Girija Theatre"
        },
        {
          "gross": 0,
          "movie": "Jana Nayagan [T]",
          "screen": "Dolby Atmos",
          "showid": "5705",
          "tickets_sold": 0,
          "time": "06:30 PM",
          "venue": "Girija Theatre"
        },
        {
          "gross": 0,
          "movie": "Jana Nayagan [T]",
          "screen": "Dolby Atmos",
          "showid": "5706",
          "tickets_sold": 0,
          "time": "09:45 PM",
          "venue": "Girija Theatre"
        }
      ],
      "shows": 4,
      "tickets_sold": 10
    },
    "Jana Nayakan": {
      "gross": 20100,
      "occupancy": null,
      "seats_type": {
        "with_gross": {
          "breakdown": [
            {
              "gross": 5850,
              "movie": "Jana Nayagan",
              "screen": "Aiswarya",
              "showid": "7813",
              "tickets_sold": 39,
              "time": "10:45 AM",
              "venue": "Aiswarya Cinemas"
            },
            {
              "gross": 5850,
              "movie": "Jana Nayagan",
              "screen": "Aiswarya",
              "showid": "7814",
              "tickets_sold": 39,
              "time": "02:15 PM",
              "venue": "Aiswarya Cinemas"
            },
            {
              "gross": 4050,
              "movie": "Jana Nayagan",
              "screen": null,
              "showid": "18927",
              "tickets_sold": 27,
              "time": "05:00 PM",
              "venue": "Puthet Cinemas"
            },
            {
              "gross": 1350,
              "movie": "Jana Nayagan",
              "screen": "Aiswarya",
              "showid": "7816",
              "tickets_sold": 9,
              "time": "09:15 PM",
              "venue": "Aiswarya Cinemas"
            },
            {
              "gross": 1050,
              "movie": "Jana Nayagan",
              "screen": null,
              "showid": "18926",
              "tickets_sold": 7,
              "time": "01:30 PM",
              "venue": "Puthet Cinemas"
            },
            {
              "gross": 900,
              "movie": "Jana Nayagan",
              "screen": null,
              "showid": "18925",
              "tickets_sold": 6,
              "time": "10:00 AM",
              "venue": "Puthet Cinemas"
            },
            {
              "gross": 600,
              "movie": "Jana Nayagan",
              "screen": null,
              "showid": "18928",
              "tickets_sold": 4,
              "time": "08:30 PM",
              "venue": "Puthet Cinemas"
            },
            {
              "gross": 450,
              "movie": "Jana Nayagan",
              "screen": "Aiswarya",
              "showid": "7815",
              "tickets_sold": 3,
              "time": "05:45 PM",
              "venue": "Aiswarya Cinemas"
            }
          ],
          "gross": 20100,
          "shows": 8,
          "tickets_sold": 134
        },
        "without_gross": {
          "breakdown": [
            {
              "gross": 0,
              "movie": "Jana Nayagan",
              "screen": null,
              "showid": "18929",
              "tickets_sold": 0,
              "time": "11:45 PM",
              "venue": "Puthet Cinemas"
            }
          ],
          "shows": 1,
          "tickets_sold": 0
        }
      },
      "show_breakdown": [
        {
          "gross": 5850,
          "movie": "Jana Nayagan",
          "screen": "Aiswarya",
          "showid": "7813",
          "tickets_sold": 39,
          "time": "10:45 AM",
          "venue": "Aiswarya Cinemas"
        },
        {
          "gross": 5850,
          "movie": "Jana Nayagan",
          "screen": "Aiswarya",
          "showid": "7814",
          "tickets_sold": 39,
          "time": "02:15 PM",
          "venue": "Aiswarya Cinemas"
        },
        {
          "gross": 4050,
          "movie": "Jana Nayagan",
          "screen": null,
          "showid": "18927",
          "tickets_sold": 27,
          "time": "05:00 PM",
          "venue": "Puthet Cinemas"
        },
        {
          "gross": 1350,
          "movie": "Jana Nayagan",
          "screen": "Aiswarya",
          "showid": "7816",
          "tickets_sold": 9,
          "time": "09:15 PM",
          "venue": "Aiswarya Cinemas"
        },
        {
          "gross": 1050,
          "movie": "Jana Nayagan",
          "screen": null,
          "showid": "18926",
          "tickets_sold": 7,
          "time": "01:30 PM",
          "venue": "Puthet Cinemas"
        },
        {
          "gross": 900,
          "movie": "Jana Nayagan",
          "screen": null,
          "showid": "18925",
          "tickets_sold": 6,
          "time": "10:00 AM",
          "venue": "Puthet Cinemas"
        },
        {
          "gross": 600,
          "movie": "Jana Nayagan",
          "screen": null,
          "showid": "18928",
          "tickets_sold": 4,
          "time": "08:30 PM",
          "venue": "Puthet Cinemas"
        },
        {
          "gross": 450,
          "movie": "Jana Nayagan",
          "screen": "Aiswarya",
          "showid": "7815",
          "tickets_sold": 3,
          "time": "05:45 PM",
          "venue": "Aiswarya Cinemas"
        },
        {
          "gross": 0,
          "movie": "Jana Nayagan",
          "screen": null,
          "showid": "18929",
          "tickets_sold": 0,
          "time": "11:45 PM",
          "venue": "Puthet Cinemas"
        }
      ],
      "shows": 9,
      "tickets_sold": 134
    },
    "Maharaja Hostel": {
      "gross": 0,
      "occupancy": null,
      "seats_type": {
        "with_gross": {
          "breakdown": [],
          "gross": 0,
          "shows": 0,
          "tickets_sold": 0
        },
        "without_gross": {
          "breakdown": [
            {
              "gross": 0,
              "movie": "Maharaja Hostel",
              "screen": "SCREEN 2",
              "showid": "3453",
              "tickets_sold": 0,
              "time": "11:15 AM",
              "venue": "Fairyland Cinemas"
            },
            {
              "gross": 0,
              "movie": "Maharaja Hostel",
              "screen": "SCREEN 2",
              "showid": "3454",
              "tickets_sold": 0,
              "time": "02:30 PM",
              "venue": "Fairyland Cinemas"
            },
            {
              "gross": 0,
              "movie": "Maharaja Hostel",
              "screen": "SCREEN 2",
              "showid": "3455",
              "tickets_sold": 0,
              "time": "06:15 PM",
              "venue": "Fairyland Cinemas"
            },
            {
              "gross": 0,
              "movie": "Maharaja Hostel",
              "screen": "SCREEN 2",
              "showid": "3456",
              "tickets_sold": 0,
              "time": "09:30 PM",
              "venue": "Fairyland Cinemas"
            }
          ],
          "shows": 4,
          "tickets_sold": 0
        }
      },
      "show_breakdown": [
        {
          "gross": 0,
          "movie": "Maharaja Hostel",
          "screen": "SCREEN 2",
          "showid": "3453",
          "tickets_sold": 0,
          "time": "11:15 AM",
          "venue": "Fairyland Cinemas"
        },
        {
          "gross": 0,
          "movie": "Maharaja Hostel",
          "screen": "SCREEN 2",
          "showid": "3454",
          "tickets_sold": 0,
          "time": "02:30 PM",
          "venue": "Fairyland Cinemas"
        },
        {
          "gross": 0,
          "movie": "Maharaja Hostel",
          "screen": "SCREEN 2",
          "showid": "3455",
          "tickets_sold": 0,
          "time": "06:15 PM",
          "venue": "Fairyland Cinemas"
        },
        {
          "gross": 0,
          "movie": "Maharaja Hostel",
          "screen": "SCREEN 2",
          "showid": "3456",
          "tickets_sold": 0,
          "time": "09:30 PM",
          "venue": "Fairyland Cinemas"
        }
      ],
      "shows": 4,
      "tickets_sold": 0
    },
    "The Odyssey": {
      "gross": 0,
      "occupancy": null,
      "seats_type": {
        "with_gross": {
          "breakdown": [],
          "gross": 0,
          "shows": 0,
          "tickets_sold": 0
        },
        "without_gross": {
          "breakdown": [
            {
              "gross": 0,
              "movie": "The Odyssey",
              "screen": "SCREEN 3",
              "showid": "3489",
              "tickets_sold": 0,
              "time": "10:45 AM",
              "venue": "Fairyland Cinemas"
            },
            {
              "gross": 0,
              "movie": "The Odyssey",
              "screen": "SCREEN 3",
              "showid": "3490",
              "tickets_sold": 0,
              "time": "02:00 PM",
              "venue": "Fairyland Cinemas"
            },
            {
              "gross": 0,
              "movie": "The Odyssey",
              "screen": "SCREEN 3",
              "showid": "3491",
              "tickets_sold": 0,
              "time": "05:45 PM",
              "venue": "Fairyland Cinemas"
            },
            {
              "gross": 0,
              "movie": "The Odyssey",
              "screen": "SCREEN 3",
              "showid": "3492",
              "tickets_sold": 0,
              "time": "09:00 PM",
              "venue": "Fairyland Cinemas"
            }
          ],
          "shows": 4,
          "tickets_sold": 0
        }
      },
      "show_breakdown": [
        {
          "gross": 0,
          "movie": "The Odyssey",
          "screen": "SCREEN 3",
          "showid": "3489",
          "tickets_sold": 0,
          "time": "10:45 AM",
          "venue": "Fairyland Cinemas"
        },
        {
          "gross": 0,
          "movie": "The Odyssey",
          "screen": "SCREEN 3",
          "showid": "3490",
          "tickets_sold": 0,
          "time": "02:00 PM",
          "venue": "Fairyland Cinemas"
        },
        {
          "gross": 0,
          "movie": "The Odyssey",
          "screen": "SCREEN 3",
          "showid": "3491",
          "tickets_sold": 0,
          "time": "05:45 PM",
          "venue": "Fairyland Cinemas"
        },
        {
          "gross": 0,
          "movie": "The Odyssey",
          "screen": "SCREEN 3",
          "showid": "3492",
          "tickets_sold": 0,
          "time": "09:00 PM",
          "venue": "Fairyland Cinemas"
        }
      ],
      "shows": 4,
      "tickets_sold": 0
    },
    "VARAVU": {
      "gross": 0,
      "occupancy": null,
      "seats_type": {
        "with_gross": {
          "breakdown": [],
          "gross": 0,
          "shows": 0,
          "tickets_sold": 0
        },
        "without_gross": {
          "breakdown": [
            {
              "gross": 0,
              "movie": "Varavu",
              "screen": "SCREEN 4",
              "showid": "3475",
              "tickets_sold": 0,
              "time": "02:15 PM",
              "venue": "Fairyland Cinemas"
            },
            {
              "gross": 0,
              "movie": "Varavu",
              "screen": "SCREEN 4",
              "showid": "3476",
              "tickets_sold": 0,
              "time": "06:00 PM",
              "venue": "Fairyland Cinemas"
            },
            {
              "gross": 0,
              "movie": "Varavu",
              "screen": "SCREEN 4",
              "showid": "3477",
              "tickets_sold": 0,
              "time": "09:15 PM",
              "venue": "Fairyland Cinemas"
            }
          ],
          "shows": 3,
          "tickets_sold": 0
        }
      },
      "show_breakdown": [
        {
          "gross": 0,
          "movie": "Varavu",
          "screen": "SCREEN 4",
          "showid": "3475",
          "tickets_sold": 0,
          "time": "02:15 PM",
          "venue": "Fairyland Cinemas"
        },
        {
          "gross": 0,
          "movie": "Varavu",
          "screen": "SCREEN 4",
          "showid": "3476",
          "tickets_sold": 0,
          "time": "06:00 PM",
          "venue": "Fairyland Cinemas"
        },
        {
          "gross": 0,
          "movie": "Varavu",
          "screen": "SCREEN 4",
          "showid": "3477",
          "tickets_sold": 0,
          "time": "09:15 PM",
          "venue": "Fairyland Cinemas"
        }
      ],
      "shows": 3,
      "tickets_sold": 0
    },
    "Varavu": {
      "gross": 0,
      "occupancy": null,
      "seats_type": {
        "with_gross": {
          "breakdown": [],
          "gross": 0,
          "shows": 0,
          "tickets_sold": 0
        },
        "without_gross": {
          "breakdown": [
            {
              "gross": 0,
              "movie": "Varavu",
              "screen": "SCREEN 4",
              "showid": "3475",
              "tickets_sold": 0,
              "time": "02:15 PM",
              "venue": "Fairyland Cinemas"
            },
            {
              "gross": 0,
              "movie": "Varavu",
              "screen": "SCREEN 4",
              "showid": "3476",
              "tickets_sold": 0,
              "time": "06:00 PM",
              "venue": "Fairyland Cinemas"
            },
            {
              "gross": 0,
              "movie": "Varavu",
              "screen": "SCREEN 4",
              "showid": "3477",
              "tickets_sold": 0,
              "time": "09:15 PM",
              "venue": "Fairyland Cinemas"
            }
          ],
          "shows": 3,
          "tickets_sold": 0
        }
      },
      "show_breakdown": [
        {
          "gross": 0,
          "movie": "Varavu",
          "screen": "SCREEN 4",
          "showid": "3475",
          "tickets_sold": 0,
          "time": "02:15 PM",
          "venue": "Fairyland Cinemas"
        },
        {
          "gross": 0,
          "movie": "Varavu",
          "screen": "SCREEN 4",
          "showid": "3476",
          "tickets_sold": 0,
          "time": "06:00 PM",
          "venue": "Fairyland Cinemas"
        },
        {
          "gross": 0,
          "movie": "Varavu",
          "screen": "SCREEN 4",
          "showid": "3477",
          "tickets_sold": 0,
          "time": "09:15 PM",
          "venue": "Fairyland Cinemas"
        }
      ],
      "shows": 3,
      "tickets_sold": 0
    }
  },
  "verification": {
    "merged_movies": [
      {
        "aliases": [
          "Jana Nayagan",
          "Jana Nayagan [T]"
        ],
        "canonical": "Jana Nayagan"
      },
      {
        "aliases": [
          "VARAVU",
          "Varavu"
        ],
        "canonical": "VARAVU"
      },
      {
        "aliases": [
          "The Odyssey"
        ],
        "canonical": "The Odyssey"
      },
      {
        "aliases": [
          "Spider-Man: Brand New Day"
        ],
        "canonical": "Spider-Man: Brand New Day"
      },
      {
        "aliases": [
          "Maharaja Hostel"
        ],
        "canonical": "Maharaja Hostel"
      },
      {
        "aliases": [
          "I, Nobody"
        ],
        "canonical": "I, Nobody"
      },
      {
        "aliases": [
          "Unknown"
        ],
        "canonical": "Unknown"
      },
      {
        "aliases": [
          "Jana Nayakan"
        ],
        "canonical": "Jana Nayakan"
      }
    ]
  }
}